qoqo_for_braket_devices-0.9.0.dist-info/METADATA
qoqo_for_braket_devices-0.9.0.dist-info/WHEEL
qoqo_for_braket_devices-0.9.0.dist-info/licenses/LICENSE
qoqo_for_braket_devices/DEPENDENCIES
qoqo_for_braket_devices/LICENSE_FOR_BINARY_DISTRIBUTION
qoqo_for_braket_devices/PYTHON_LICENSE
qoqo_for_braket_devices/__init__.py
qoqo_for_braket_devices/qoqo_for_braket_devices.cp312-win_amd64.pyd
qoqo_for_braket_devices-0.9.0.dist-info/RECORD
